CONTRIBUTING.md
LICENSE
MANIFEST.in
README.md
VERSION
setup.cfg
setup.py
docs/Makefile
docs/conf.py
docs/index.rst
docs/make.bat
src/viskit/__init__.py
src/viskit/core.py
src/viskit/frontend.py
src/viskit.egg-info/PKG-INFO
src/viskit.egg-info/SOURCES.txt
src/viskit.egg-info/dependency_links.txt
src/viskit.egg-info/requires.txt
src/viskit.egg-info/top_level.txt
src/viskit/misc/__init__.py
src/viskit/misc/ext.py
tests/__init__.py
tests/viskit/__init__.py
tests/viskit/misc/test_ext.py