Metadata-Version: 2.1
Name: viskit
Version: 0.0.3
Summary: Hyperparameter dashboard for reinforcement learning experiments
Home-page: https://github.com/rlworkgroup/viskit
Author: Reinforcement Learning Working Group
Author-email: viskit@noreply.github.com
License: MIT
Platform: UNKNOWN
Classifier: Development Status :: 4 - Beta
Classifier: Intended Audience :: Developers
Classifier: Intended Audience :: Education
Classifier: Intended Audience :: Science/Research
Classifier: License :: OSI Approved :: MIT License
Classifier: Programming Language :: Python :: 3.5
Classifier: Programming Language :: Python :: 3.6
Classifier: Programming Language :: Python :: 3.7
Classifier: Programming Language :: Python :: 3 :: Only
Classifier: Topic :: Scientific/Engineering :: Artificial Intelligence
Classifier: Topic :: Scientific/Engineering :: Mathematics
Classifier: Topic :: Software Development :: Libraries
Provides-Extra: all
Provides-Extra: dev
